[
    {
        "source": "Image_114233.png",
        "qid": "QID:000101",
        "question_number": 1,
        "question": "What is the capital of France ? ",
        "options": [
            "Paris",
            "Lyon",
            "Marseille",
            "Versaille"
        ],
        "correct_index": "",
        "explanation": "Bla Bla Bla.",
        "category": "KA=Initiating"
    },
    {
        "source": "Image_114301.png",
        "qid": "QID:000102",
        "question_number": 2,
        "question": "which is not a city of Texas ?",
        "options": [
            "Austin",
            "Dallas",
            "Houston",
            "Pensilvania"
        ],
        "correct_index": "",
        "explanation": "Bla Bla Bla.",
        "category": "KA=Initiating"
    },
    {
        "source": "Image_174554.png",
        "qid": "QID:000103",
        "question_number": 3,
        "question": "Biggest city of USA ?",
        "options": [
            "Minesota",
            "Alaska",
            "Hawai",
            "Chicago"
        ],
        "correct_index": "B",
        "explanation": "Bla Bla Bla.",
        "category": "KA=Initiating"
    }
]